dfir_unfurl-20250810.dist-info/licenses/LICENSE
unfurl/__init__.py
unfurl/app.py
unfurl/cli.py
unfurl/core.py
unfurl/utils.py
unfurl/parsers/__init__.py
unfurl/parsers/parse_base64.py
unfurl/parsers/parse_bing.py
unfurl/parsers/parse_bluesky.py
unfurl/parsers/parse_brave.py
unfurl/parsers/parse_compressed.py
unfurl/parsers/parse_discord.py
unfurl/parsers/parse_dns.py
unfurl/parsers/parse_domain.py
unfurl/parsers/parse_dropbox.py
unfurl/parsers/parse_duckduckgo.py
unfurl/parsers/parse_google.py
unfurl/parsers/parse_hash.py
unfurl/parsers/parse_initial_node.py
unfurl/parsers/parse_ip.py
unfurl/parsers/parse_json.py
unfurl/parsers/parse_jwt.py
unfurl/parsers/parse_ksuid.py
unfurl/parsers/parse_linkedin.py
unfurl/parsers/parse_mac_addr.py
unfurl/parsers/parse_magnet.py
unfurl/parsers/parse_mailto.py
unfurl/parsers/parse_mastodon.py
unfurl/parsers/parse_metasploit.py
unfurl/parsers/parse_protobuf.py
unfurl/parsers/parse_shortlink.py
unfurl/parsers/parse_sonyflake.py
unfurl/parsers/parse_tiktok.py
unfurl/parsers/parse_timestamp.py
unfurl/parsers/parse_trackers.py
unfurl/parsers/parse_twitter.py
unfurl/parsers/parse_ulid.py
unfurl/parsers/parse_url.py
unfurl/parsers/parse_uuid.py
unfurl/parsers/parse_yahoo.py
unfurl/parsers/parse_youtube.py
unfurl/parsers/proto/__init__.py
unfurl/parsers/proto/google_search.proto
unfurl/parsers/proto/google_search_pb2.py
unfurl/scripts/unfurl_app.py
unfurl/scripts/unfurl_cli.py
unfurl/static/android-chrome-192x192.png
unfurl/static/android-chrome-512x512.png
unfurl/static/apple-touch-icon.png
unfurl/static/favicon-16x16.png
unfurl/static/favicon-32x32.png
unfurl/static/favicon.ico
unfurl/static/site.webmanifest
unfurl/static/styles.css
unfurl/static/unfurl-3d.gif
unfurl/static/unfurl.png
unfurl/static/unfurl_dark.png
unfurl/templates/base.html
unfurl/templates/graph.html
unfurl/tests/__init__.py
unfurl/tests/integration/__init__.py
unfurl/tests/integration/test_api.py
unfurl/tests/unit/__init__.py
unfurl/tests/unit/test_base64.py
unfurl/tests/unit/test_bing.py
dfir_unfurl-20250810.dist-info/METADATA
dfir_unfurl-20250810.dist-info/WHEEL
dfir_unfurl-20250810.dist-info/entry_points.txt
dfir_unfurl-20250810.dist-info/top_level.txt
dfir_unfurl-20250810.dist-info/RECORD
