Metadata-Version: 2.4
Name: dfir-unfurl
Version: 20250810
Summary: Unfurl takes a URL and expands ("unfurls") it into a directed graph
Author-email: Ryan Benson <ryan@dfir.blog>
License: 
Project-URL: Home, https://github.com/obsidianforensics/unfurl
Keywords: unfurl,forensics,dfir,reverse-engineering,security,osint,digital forensics
Classifier: License :: OSI Approved :: Apache Software License
Classifier: Programming Language :: Python :: 3
Requires-Python: >=3.11
License-File: LICENSE
Requires-Dist: bbpb>=1.4.1
Requires-Dist: dnslib<1
Requires-Dist: netaddr>=1.3.0
Requires-Dist: networkx==3.*
Requires-Dist: protobuf<6.0,>=4.0
Requires-Dist: publicsuffix2
Requires-Dist: pycountry>24
Requires-Dist: pymispwarninglists>=1.6.1
Requires-Dist: requests>=2.32
Requires-Dist: torf>4
Requires-Dist: ulid-py>1
Provides-Extra: ui
Requires-Dist: flask>=3.0.0; extra == "ui"
Requires-Dist: flask-restx>=1.3.0; extra == "ui"
Requires-Dist: flask_cors; extra == "ui"
Requires-Dist: Werkzeug>=3.0.0; extra == "ui"
Provides-Extra: all
Requires-Dist: dfir-unfurl[ui]; extra == "all"
Dynamic: license-file
